{
    "pron": [
        "gō",
        "Yā'ōẏā"
    ],
    "bn": "যাওয়া",
    "en": "go",
    "bn_syns": [
        "তেজ",
        "যাওয়া",
        "এগোনো",
        "ছেড়ে যাওয়া",
        "বিদায় হওয়া",
        "হত্তয়া",
        "চালু হত্তয়া",
        "বর্তমানে চালু থাকা",
        "উদ্যত হত্তয়া",
        "উপক্রম করা",
        "প্রসারিত হত্তয়া",
        "ঝোঁকা",
        "অভিমুখ হত্তয়া",
        "বাজা",
        "যাত্তয়া",
        "সক্রিয় হত্তয়া",
        "প্রস্থান করা",
        "ধাবন করা",
        "অগ্রসর হত্তয়া",
        "নড়া",
        "গমন করা",
        "চলা",
        "গণ্য হত্তয়া",
        "বিদিত থাকা",
        "সচরাচর হত্তয়া",
        "গর্ভবতী হত্তয়া",
        "পরিপূর্ণ হত্তয়া",
        "ঘটা",
        "পরিণত হত্তয়া",
        "অকৃতকার্য হত্তয়া",
        "অন্তর্ভুক্ত হত্তয়া",
        "পথ ছাড়িয়া দেত্তয়া",
        "মানানসই হত্তয়া",
        "অনুধাবন করা",
        "বাজি ধরা",
        "ডাক দেত্তয়া",
        "বলবৎ থাকা",
        "গমন",
        "গতি",
        "ব্যাপার",
        "সফল অভিযান",
        "কার্যকরতা",
        "কর্মশক্তি",
        "সক্রিয়তা",
        "প্রচেষ্টা"
    ],
    "en_syns": [
        "move",
        "proceed",
        "make one's way",
        "advance",
        "progress",
        "pass",
        "walk",
        "travel",
        "journey",
        "betake oneself",
        "attempt",
        "try",
        "effort",
        "bid",
        "endeavor",
        "shot",
        "stab",
        "crack",
        "bash",
        "whirl",
        "whack",
        "essay"
    ],
    "sents": [
        "she's prepared to <b>go</b> up to Є25,000",
        "millions <b>go</b> hungry all over the world"
    ]
}